MANIFEST.in
README
setup.py
gefr/__init__.py
gefr/core.py
gefr/wsgi.py
gefr.egg-info/PKG-INFO
gefr.egg-info/SOURCES.txt
gefr.egg-info/dependency_links.txt
gefr.egg-info/requires.txt
gefr.egg-info/top_level.txt
gefr/backends/__init__.py
gefr/backends/jetty.py
gefr/backends/mina.py
gefr/backends/netty.py
gefr/backends/soldat.py