Metadata-Version: 1.0
Name: gefr
Version: 0.3
Summary: A suite of WSGI bridges to Java servers.
Home-page: https://bitbucket.org/sunng/gefr
Author: Sun Ning
Author-email: classicning@gmail.com
License: mit
Platform: UNKNOWN
Classifier: Development Status :: 3 - Alpha
Classifier: Intended Audience :: Developers
Classifier: License :: OSI Approved :: MIT License
Classifier: Topic :: Internet :: WWW/HTTP :: WSGI :: Server
Classifier: Programming Language :: Python :: 2.5
Classifier: Programming Language :: Java
Classifier: Environment :: Web Environment
Classifier: Operating System :: POSIX
